LICENSE
MANIFEST.in
README.rst
setup.py
guzzle_sphinx_theme/__init__.py
guzzle_sphinx_theme/guzzle_sphinx_theme/globaltoc.html
guzzle_sphinx_theme/guzzle_sphinx_theme/layout.html
guzzle_sphinx_theme/guzzle_sphinx_theme/localtoc.html
guzzle_sphinx_theme/guzzle_sphinx_theme/search.html
guzzle_sphinx_theme/guzzle_sphinx_theme/searchbox.html
guzzle_sphinx_theme/guzzle_sphinx_theme/theme.conf
guzzle_sphinx_theme/guzzle_sphinx_theme/static/guzzle.css_t
guzzle_sphinx_theme/guzzle_sphinx_theme/static/jquery.js
guzzle_sphinx_theme/guzzle_sphinx_theme/static/jquery.min.map
guzzle_sphinx_theme/guzzle_sphinx_theme/static/css/bootstrap-theme.min.css
guzzle_sphinx_theme/guzzle_sphinx_theme/static/css/bootstrap.min.css
guzzle_sphinx_theme/guzzle_sphinx_theme/static/fonts/glyphicons-halflings-regular.eot
guzzle_sphinx_theme/guzzle_sphinx_theme/static/fonts/glyphicons-halflings-regular.svg
guzzle_sphinx_theme/guzzle_sphinx_theme/static/fonts/glyphicons-halflings-regular.ttf
guzzle_sphinx_theme/guzzle_sphinx_theme/static/fonts/glyphicons-halflings-regular.woff
guzzle_sphinx_theme/guzzle_sphinx_theme/static/fonts/roboto-slab-v10-latin-500.woff
guzzle_sphinx_theme/guzzle_sphinx_theme/static/fonts/roboto-slab-v10-latin-500.woff2
guzzle_sphinx_theme/guzzle_sphinx_theme/static/js/bootstrap.js
guzzle_sphinx_theme/guzzle_sphinx_theme/static/js/bootstrap.min.js
guzzle_sphinx_theme/guzzle_sphinx_theme/static/js/jquery.min.js
pyinfra_guzzle_sphinx_theme.egg-info/PKG-INFO
pyinfra_guzzle_sphinx_theme.egg-info/SOURCES.txt
pyinfra_guzzle_sphinx_theme.egg-info/dependency_links.txt
pyinfra_guzzle_sphinx_theme.egg-info/requires.txt
pyinfra_guzzle_sphinx_theme.egg-info/top_level.txt