Metadata-Version: 2.4
Name: pyinfra-guzzle_sphinx_theme
Version: 0.19
Summary: Sphinx theme used by Guzzle, with customisations for pyinfra.
Home-page: https://github.com/Fizzadar/guzzle_sphinx_theme
Author: Michael Dowling (modified by Nick Barrett)
Author-email: pointlessrambler@gmail.com
License: MIT
Classifier: Development Status :: 3 - Alpha
Classifier: Intended Audience :: Developers
Classifier: Natural Language :: English
Classifier: License :: OSI Approved :: MIT License
Classifier: Programming Language :: Python
License-File: LICENSE
Requires-Dist: Sphinx>1.3
Dynamic: author
Dynamic: author-email
Dynamic: classifier
Dynamic: home-page
Dynamic: license
Dynamic: license-file
Dynamic: requires-dist
Dynamic: summary
